fonk/__init__.py
fonk/__main__.py
fonk/cli.py
fonk/config.py
fonk/locator.py
fonk/render.py
fonk/runner.py
fonk/session.py
fonk-0.1.1.dist-info/METADATA
fonk-0.1.1.dist-info/WHEEL
fonk-0.1.1.dist-info/entry_points.txt
fonk-0.1.1.dist-info/licenses/LICENSE.md
fonk-0.1.1.dist-info/RECORD
