Metadata-Version: 2.4
Name: fonk
Version: 0.1.1
Summary: fonk: pyproject.toml based task runner
Author-email: Thijs Miedema <opensource@tmiedema.com>
License-File: LICENSE.md
Classifier: Development Status :: 3 - Alpha
Classifier: Intended Audience :: Developers
Classifier: License :: OSI Approved :: MIT License
Classifier: Programming Language :: Python :: 3
Requires-Python: >=3.11
Requires-Dist: rich>=13.9.4
Requires-Dist: tomli>=2.2.1
